py_consistent_formatter/__init__.py
py_consistent_formatter/__main__.py
py_consistent_formatter/formatter.py
py_consistent_formatter/sort_all.py
py_consistent_formatter-1.3.0.dist-info/METADATA
py_consistent_formatter-1.3.0.dist-info/WHEEL
py_consistent_formatter-1.3.0.dist-info/entry_points.txt
py_consistent_formatter-1.3.0.dist-info/RECORD
