Metadata-Version: 2.4
Name: py-consistent-formatter
Version: 1.3.0
Author: Marek Antoniak
Requires-Python: >=3.11
Requires-Dist: docformatter~=1.7
Requires-Dist: isort~=7.0
Requires-Dist: tokenize-rt~=6.0
Requires-Dist: yapf~=0.40
